trax/libtrax.so
trax/image.py
trax/region.py
trax/__init__.py
trax/_ctypes.py
trax/client.py
trax/server.py
vot_trax-4.0.2.dist-info/RECORD
vot_trax-4.0.2.dist-info/top_level.txt
vot_trax-4.0.2.dist-info/WHEEL
vot_trax-4.0.2.dist-info/METADATA
