Metadata-Version: 2.1
Name: vot-trax
Version: 4.0.2
Summary: TraX protocol reference implementation wrapper for Python
Home-page: https://github.com/votchallenge/trax/
Author: Luka Cehovin Zajc
Author-email: luka.cehovin@gmail.com
Classifier: Programming Language :: Python :: 3
Classifier: License :: OSI Approved :: BSD License
Classifier: Development Status :: 5 - Production/Stable
Classifier: Intended Audience :: Science/Research
Requires-Dist: numpy >=1.16
Requires-Dist: six
